nemoai/__init__.py
nemoai/sample/__init__.py
nemoai/sample/math.py
tests/__init__.py
nemoai_package-0.1.1.dist-info/METADATA
nemoai_package-0.1.1.dist-info/WHEEL
nemoai_package-0.1.1.dist-info/top_level.txt
nemoai_package-0.1.1.dist-info/RECORD
